pmtk/__init__.py
pmtk/main.py
pmtk-0.1.4.dist-info/LICENSE.txt
pmtk-0.1.4.dist-info/METADATA
pmtk-0.1.4.dist-info/WHEEL
pmtk-0.1.4.dist-info/top_level.txt
pmtk-0.1.4.dist-info/RECORD
