Metadata-Version: 2.1
Name: pmtk
Version: 0.1.4
Summary: A package providing project management tools like NetworkDiagram and NetworkDiagramExporter.
Home-page: https://github.com/Yasayah-Nadeem-Khokhar/pmtk
Author: Yasayah Nadeem Khokhar
Author-email: yasayahnadeem22@gmail.com
License: MIT
Classifier: Programming Language :: Python :: 3
Classifier: License :: OSI Approved :: MIT License
Classifier: Operating System :: OS Independent
Requires-Python: >=3.7
License-File: LICENSE.txt
Requires-Dist: pandas
